README.rst
setup.py
ipynb_format/__init__.py
ipynb_format.egg-info/PKG-INFO
ipynb_format.egg-info/SOURCES.txt
ipynb_format.egg-info/dependency_links.txt
ipynb_format.egg-info/entry_points.txt
ipynb_format.egg-info/requires.txt
ipynb_format.egg-info/top_level.txt