Metadata-Version: 1.1
Name: ipynb-format
Version: 0.1.1
Summary: A code formatter for python code in ipython notebooks
Home-page: https://github.com/fg1/ipynb_format
Author: fg1
Author-email: UNKNOWN
License: BSD
Keywords: ipython notebook
Platform: UNKNOWN
Classifier: Development Status :: 3 - Alpha
Classifier: Environment :: Console
Classifier: Intended Audience :: Science/Research
Classifier: License :: OSI Approved :: BSD License
Classifier: Programming Language :: Python :: 2
Classifier: Programming Language :: Python :: 2.6
Classifier: Programming Language :: Python :: 2.7
Classifier: Programming Language :: Python :: 3
